pyqt_foldable_toolbar/__init__.py
pyqt_foldable_toolbar/foldableToolBar.py
pyqt_foldable_toolbar/ico/__init__.py
pyqt_foldable_toolbar/ico/fold.svg
pyqt_foldable_toolbar/ico/unfold.svg
pyqt_foldable_toolbar-0.0.11.dist-info/LICENSE
pyqt_foldable_toolbar-0.0.11.dist-info/METADATA
pyqt_foldable_toolbar-0.0.11.dist-info/WHEEL
pyqt_foldable_toolbar-0.0.11.dist-info/top_level.txt
pyqt_foldable_toolbar-0.0.11.dist-info/RECORD
