Metadata-Version: 2.1
Name: pyqt-foldable-toolbar
Version: 0.0.11
Summary: PyQt foldable toolbar
Home-page: https://github.com/yjg30737/pyqt-foldable-toolbar.git
Author: Jung Gyu Yoon
Author-email: yjg30737@gmail.com
License: MIT
Platform: UNKNOWN
License-File: LICENSE
Requires-Dist: PyQt5 (>=5.8)
Requires-Dist: pyqt-svg-button (>=0.0.1)
